{
  "extends": "tslint:latest",
  "rules": {
    "arrow-parens": [
      true,
      "ban-single-arg-parens"
    ],
    "interface-name": [
      true,
      "never-prefix"
    ],
    "member-ordering": [
      true,
      {
        "order": [
          "private-static-field",
          "private-static-method",
          "protected-static-field",
          "protected-static-method",
          "public-static-field",
          "public-static-method",
          "private-instance-field",
          "protected-instance-field",
          "public-instance-field",
          "private-constructor",
          "protected-constructor",
          "public-constructor",
          "private-instance-method",
          "protected-instance-method",
          "public-instance-method"
        ]
      }
    ],
    "no-shadowed-variable": false,
    "no-object-literal-type-assertion": false,
    "no-string-literal": false,
    "object-literal-sort-keys": false,
    "ordered-imports": false,
    "prefer-conditional-expression": false,
    "prefer-for-of": false,
    "prefer-object-spread": false,
    "quotemark": [
      true,
      "single"
    ],
    "trailing-comma": [
      false
    ],
    "whitespace": [
      true,
      "check-branch",
      "check-decl",
      "check-operator",
      "check-module",
      "check-separator",
      "check-type"
    ]
  }
}